README.md
setup.py
question_intimacy/__init__.py
question_intimacy/play.py
question_intimacy/predict_intimacy.py
question_intimacy.egg-info/PKG-INFO
question_intimacy.egg-info/SOURCES.txt
question_intimacy.egg-info/dependency_links.txt
question_intimacy.egg-info/top_level.txt