Metadata-Version: 2.1
Name: question-intimacy
Version: 1.1
Summary: This package is used to predict intimacy for questions
Home-page: UNKNOWN
Author: Jiaxin Pei
Author-email: pedropei@umich.edu
License: UNKNOWN
Platform: UNKNOWN
Requires-Python: >=3.6
